{
    "items": [
        {
            "sentence": "[](%L) De  [hele]0  [stad]0 [](L%) [](%L) met  [alle]0 [omliggende]0 [dorpen]0 []2",
            "key": ["%L", "H*", "!H*L", "L%", "%L","H*", "∅", "!H*L", "L%"],
            "contour": "4B-1.png", 
            "audio": "4B-1.mp3"
        },
        {
            "sentence": "[](%L) Maar [dat]0  soort [dingen]0 [](H%) [](%L) zijn er [niet]0 [bij]0 [](L%)",
            "key": ["%L", "H*L", "∅", "H%","%L","∅","H*L","L%"],
            "contour": "4B-2.png", 
            "audio": "4B-2.mp3"
        },
        {
            "sentence": "[](%L) [Is die]0  [rekening]0 al [betaald]0 [](H%)",
            "key": ["%L","∅", "H*L","∅", "H%"],
            "contour": "4B-3.png", 
            "audio": "4B-3.mp3"
        },
        {
            "sentence": "[](%L) Maar  we  [hoeven 't]0  niet  eeh  te  [proberen]0 [](L%)",
            "key": ["%L", "H*", "!H*L","L%"],
            "contour": "4B-4.png", 
            "audio": "4B-4.mp3"
        },
        {
            "sentence": "[](%L) Er  [zijn]0 toch  niet  meer [trainers]0 [](H%)",
            "key": ["%L", "H*L","∅","H%"],
            "contour": "4B-5.png", 
            "audio": "4B-5.mp3"
        },
        {
            "sentence": "[](%L) Dat  is  uberhaupt  niet  het  geval   [](L%)",
            "key": ["%L", "H*L","∅","L%"],
            "contour": "4B-6.png", 
            "audio": "4B-6.mp3"
        },
        {
            "sentence": "[](%L) Een [mobiele]0 [telefoon]0 [](H%) [](%H) heeft-ie soms [pootjes] [](L%)",
            "key": ["%L", "H*","%"],
            "contour": "4B-7.png", 
            "audio": "4B-7.mp3"
        },
        {
            "sentence": "[](%L) Als het [water]0  tot  [hier]0  komt [](H%) [](%L) [dan]0  moet je [hozen]0 [](L%)",
            "key": ["%L", "H*L","∅","H%", "%L","H*","!H*L","L%"],
            "contour": "4B-8.png", 
            "audio": "4B-8.mp3"
        },
        {
            "sentence": "[](%L) Daar  gaan  de  [Rijke]0 [](%) [](%L) [Meulenmeester]0 [](%) [](%L) en  Versmissen [](%) [](%L) door  de  [derde]0  [bocht]0  [](%)",
            "key": ["%L", "H*","%","L%","H*","%","L%","H*","%", "L%", "H*L","H*", "%"],
            "contour": "4B-9.png", 
            "audio": "4B-9.mp3"
        },
        {
            "sentence": "[](%HL) Je [weet]0 toch  wel  wanneer  je  [eigen]0  [zoon]0  [jarig]0  is [](H%)",
            "key": ["%HL", "∅","∅","!H*L","∅","H%"],
            "contour": "4B-10.png", 
            "audio": "4B-10.mp3"
        },
        {
            "sentence": "[](%L) Als  [ik]0  nou  je [huiswerk]0  maak [](L%) [](%L) plak  [jij]0  dan  mijn  [band]0 [](H%)",
            "key": ["%L", "H*L", "H*L", "L%","L%","!H*L","∅","H%"],
            "contour": "4B-11.png", 
            "audio": "4B-11.mp3"
        },
        {
            "sentence": "[](%L) We  [hebben]0 niet  meer [smaken]0 [](%) [](%H) [geloof]0  je het [zelf]0 [](H%)",
            "key": ["%L", "L*", "∅", "%","%H","∅","H*", "H%"],
            "contour": "4B-12.png", 
            "audio": "4B-12.mp3"
        }
        
 
    ],
    "choices": [
        [
            ["H*L","!H*L"],
            ["H*","!H*"],
            ["L*","H*!H"],
            ["H*LH" ,"∅" ]

        ]
    ]
}